basisgen/__init__.py
basisgen/algebras.py
basisgen/containers.py
basisgen/eft.py
basisgen/lorentz.py
basisgen/parsing.py
basisgen/partitions.py
basisgen/representations.py
basisgen/shortcuts.py
basisgen/smeft.py
basisgen/statistics.py
basisgen/weights.py
basisgen-1.0.4.dist-info/LICENSE
basisgen-1.0.4.dist-info/METADATA
basisgen-1.0.4.dist-info/WHEEL
basisgen-1.0.4.dist-info/top_level.txt
basisgen-1.0.4.dist-info/RECORD
