Metadata-Version: 2.1
Name: basisgen
Version: 1.0.4
Summary: Package for the generation of operator bases
Home-page: https://github.com/jccriado/basisgen
Author: Juan Carlos Criado
Author-email: jccriadoalamo@ugr.es
License: MIT
Classifier: Intended Audience :: Science/Research
Classifier: License :: OSI Approved :: MIT License
Classifier: Operating System :: OS Independent
Classifier: Programming Language :: Python :: 3
Classifier: Programming Language :: Python :: 3.5
Classifier: Topic :: Scientific/Engineering :: Mathematics
Classifier: Topic :: Scientific/Engineering :: Physics
License-File: LICENSE
